{
  "updated": "2026-06-08T13:18:10",
  "account": {
    "equity": 101.09,
    "balance": 115.87,
    "available": 0
  },
  "positions": [
    {
      "coin": "LPT",
      "symbol": "LPTUSDT",
      "side": "Buy",
      "size": "46",
      "entry": 1.813,
      "markPrice": 1.809,
      "liqPrice": "1.696",
      "upnl": -0.184,
      "margin": 6.99,
      "leverage": "12",
      "sl": "1.75",
      "tp": "1.819"
    },
    {
      "coin": "ADA",
      "symbol": "ADAUSDT",
      "side": "Buy",
      "size": "491",
      "entry": 0.171,
      "markPrice": 0.1677,
      "liqPrice": "0.158",
      "upnl": -1.6203,
      "margin": 7.04,
      "leverage": "12",
      "sl": "0.1653",
      "tp": "0.1725"
    },
    {
      "coin": "TON",
      "symbol": "TONUSDT",
      "side": "Buy",
      "size": "47.5",
      "entry": 1.77105,
      "markPrice": 1.7461,
      "liqPrice": "1.6399",
      "upnl": -1.1851,
      "margin": 7.05,
      "leverage": "12",
      "sl": "1.7086",
      "tp": "1.7866"
    },
    {
      "coin": "ICP",
      "symbol": "ICPUSDT",
      "side": "Buy",
      "size": "35.1",
      "entry": 2.392,
      "markPrice": 2.358,
      "liqPrice": "2.215",
      "upnl": -1.1934,
      "margin": 7.04,
      "leverage": "12",
      "sl": "2.31",
      "tp": "2.407"
    },
    {
      "coin": "JASMY",
      "symbol": "JASMYUSDT",
      "side": "Buy",
      "size": "17338",
      "entry": 0.004842,
      "markPrice": 0.004772,
      "liqPrice": "0.004193",
      "upnl": -1.2111,
      "margin": 12.03,
      "leverage": "7",
      "sl": "0.004738",
      "tp": "0.004875"
    },
    {
      "coin": "HYPE",
      "symbol": "HYPEUSDT",
      "side": "Buy",
      "size": "1",
      "entry": 65.00977,
      "markPrice": 63.886,
      "liqPrice": "59.995",
      "upnl": -1.1238,
      "margin": 5.45,
      "leverage": "12",
      "sl": "62.997",
      "tp": "65.932"
    },
    {
      "coin": "TRX",
      "symbol": "TRXUSDT",
      "side": "Buy",
      "size": "149",
      "entry": 0.32775,
      "markPrice": 0.32556,
      "liqPrice": "0.28306",
      "upnl": -0.3263,
      "margin": 7.0,
      "leverage": "7",
      "sl": "0.30905",
      "tp": "0.32836"
    },
    {
      "coin": "CFX",
      "symbol": "CFXUSDT",
      "side": "Buy",
      "size": "1804",
      "entry": 0.04656,
      "markPrice": 0.04617,
      "liqPrice": "0.04356",
      "upnl": -0.7036,
      "margin": 7.04,
      "leverage": "12",
      "sl": "0.04498",
      "tp": "0.04685"
    },
    {
      "coin": "LINK",
      "symbol": "LINKUSDT",
      "side": "Buy",
      "size": "10.4",
      "entry": 8.059,
      "markPrice": 7.984,
      "liqPrice": "7.463",
      "upnl": -0.78,
      "margin": 7.03,
      "leverage": "12",
      "sl": "7.79",
      "tp": "8.11"
    },
    {
      "coin": "DYDX",
      "symbol": "DYDXUSDT",
      "side": "Buy",
      "size": "581",
      "entry": 0.14431,
      "markPrice": 0.14404,
      "liqPrice": "0.13363",
      "upnl": -0.1569,
      "margin": 7.03,
      "leverage": "12",
      "sl": "0.13958",
      "tp": "0.14563"
    },
    {
      "coin": "SEI",
      "symbol": "SEIUSDT",
      "side": "Buy",
      "size": "972",
      "entry": 0.050404,
      "markPrice": 0.04952,
      "liqPrice": "0.04365",
      "upnl": -0.8597,
      "margin": 7.02,
      "leverage": "7",
      "sl": "0.04749",
      "tp": "0.05079"
    },
    {
      "coin": "IMX",
      "symbol": "IMXUSDT",
      "side": "Buy",
      "size": "343",
      "entry": 0.14259,
      "markPrice": 0.13986,
      "liqPrice": "0.12321",
      "upnl": -0.9364,
      "margin": 7.01,
      "leverage": "7",
      "sl": "0.13454",
      "tp": "0.14449"
    },
    {
      "coin": "OP",
      "symbol": "OPUSDT",
      "side": "Buy",
      "size": "493",
      "entry": 0.09948,
      "markPrice": 0.09713,
      "liqPrice": "0.08613",
      "upnl": -1.1585,
      "margin": 7.03,
      "leverage": "7",
      "sl": "0.09372",
      "tp": "0.10036"
    },
    {
      "coin": "IP",
      "symbol": "IPUSDT",
      "side": "Buy",
      "size": "152",
      "entry": 0.3218,
      "markPrice": 0.3143,
      "liqPrice": "0.2787",
      "upnl": -1.14,
      "margin": 7.01,
      "leverage": "7",
      "sl": "0.3036",
      "tp": "0.3257"
    },
    {
      "coin": "SOL",
      "symbol": "SOLUSDT",
      "side": "Buy",
      "size": "1.2",
      "entry": 67.76,
      "markPrice": 66.742,
      "liqPrice": "62.43",
      "upnl": -1.2216,
      "margin": 6.82,
      "leverage": "12",
      "sl": "65.5",
      "tp": "67.95"
    },
    {
      "coin": "NEO",
      "symbol": "NEOUSDT",
      "side": "Buy",
      "size": "37.8",
      "entry": 2.222,
      "markPrice": 2.195,
      "liqPrice": "2.058",
      "upnl": -1.0206,
      "margin": 7.04,
      "leverage": "12",
      "sl": "2.149",
      "tp": "2.236"
    }
  ],
  "stats": {
    "total_trades": 854,
    "total_pnl": 60.6641,
    "wins": 689,
    "losses": 165
  }
}