{
  "last_update": "2026-05-28T13:34:31+00:00",
  "btc_summary_15m": {
    "long_liqs": 5,
    "short_liqs": 1,
    "long_vol": 825900,
    "short_vol": 160000,
    "bias": "BEARISH"
  },
  "coins": {
    "XLM": {
      "last_liq": {
        "dir": "Short",
        "amount": 75700.0,
        "price": 0.198,
        "ts": "2026-05-28T13:21:32+00:00"
      },
      "recent_15m": {
        "long_count": 0,
        "short_count": 1,
        "long_vol": 0,
        "short_vol": 75700
      }
    },
    "TON": {
      "last_liq": {
        "dir": "Long",
        "amount": 79500.0,
        "price": 1.747,
        "ts": "2026-05-28T13:22:31+00:00"
      },
      "recent_15m": {
        "long_count": 1,
        "short_count": 0,
        "long_vol": 79500,
        "short_vol": 0
      }
    },
    "BTC": {
      "last_liq": {
        "dir": "Long",
        "amount": 59600.0,
        "price": 72907.2,
        "ts": "2026-05-28T13:34:31+00:00"
      },
      "recent_15m": {
        "long_count": 5,
        "short_count": 1,
        "long_vol": 825900,
        "short_vol": 160000
      }
    },
    "AAVE": {
      "last_liq": {
        "dir": "Long",
        "amount": 71400.0,
        "price": 79.92,
        "ts": "2026-05-28T13:26:39+00:00"
      },
      "recent_15m": {
        "long_count": 1,
        "short_count": 0,
        "long_vol": 71400,
        "short_vol": 0
      }
    },
    "ETH": {
      "last_liq": {
        "dir": "Long",
        "amount": 186000.0,
        "price": 1979.42,
        "ts": "2026-05-28T13:26:44+00:00"
      },
      "recent_15m": {
        "long_count": 1,
        "short_count": 0,
        "long_vol": 186000,
        "short_vol": 0
      }
    },
    "MU": {
      "last_liq": {
        "dir": "Short",
        "amount": 121000.0,
        "price": 941.54,
        "ts": "2026-05-28T13:30:20+00:00"
      },
      "recent_15m": {
        "long_count": 0,
        "short_count": 1,
        "long_vol": 0,
        "short_vol": 121000
      }
    },
    "WLD": {
      "last_liq": {
        "dir": "Short",
        "amount": 87200.0,
        "price": 0.291,
        "ts": "2026-05-28T13:33:36+00:00"
      },
      "recent_15m": {
        "long_count": 0,
        "short_count": 1,
        "long_vol": 0,
        "short_vol": 87200
      }
    }
  }
}