{
  "last_update": "2026-05-28T17:12:12+00:00",
  "btc_summary_15m": {
    "long_liqs": 0,
    "short_liqs": 0,
    "long_vol": 0,
    "short_vol": 0,
    "bias": "NEUTRAL"
  },
  "coins": {
    "ETH": {
      "last_liq": {
        "dir": "Short",
        "amount": 61000.0,
        "price": 2014.87,
        "ts": "2026-05-28T17:12:12+00:00"
      },
      "recent_15m": {
        "long_count": 0,
        "short_count": 2,
        "long_vol": 0,
        "short_vol": 162000
      }
    },
    "XAU": {
      "last_liq": {
        "dir": "Short",
        "amount": 58700.0,
        "price": 4514.27,
        "ts": "2026-05-28T17:01:03+00:00"
      },
      "recent_15m": {
        "long_count": 0,
        "short_count": 1,
        "long_vol": 0,
        "short_vol": 58700
      }
    },
    "XLM": {
      "last_liq": {
        "dir": "Short",
        "amount": 80700.0,
        "price": 0.208,
        "ts": "2026-05-28T17:08:46+00:00"
      },
      "recent_15m": {
        "long_count": 0,
        "short_count": 1,
        "long_vol": 0,
        "short_vol": 80700
      }
    }
  }
}