{
  "positions": [
    {
      "symbol": "GLMUSDT",
      "side": "Sell",
      "size": "588",
      "avgPrice": "0.11886014",
      "markPrice": "0.11862",
      "liqPrice": "0.12818",
      "unrealisedPnl": "0.1412",
      "leverage": "10",
      "takeProfit": "0.11822",
      "stopLoss": "0.12361"
    },
    {
      "symbol": "OPUSDT",
      "side": "Sell",
      "size": "682.9",
      "avgPrice": "0.10260144",
      "markPrice": "0.10195",
      "liqPrice": "0.11174",
      "unrealisedPnl": "0.444869",
      "leverage": "10",
      "takeProfit": "0.10086",
      "stopLoss": "0.1066"
    },
    {
      "symbol": "EIGENUSDT",
      "side": "Sell",
      "size": "420",
      "avgPrice": "0.16701543",
      "markPrice": "0.16556",
      "liqPrice": "0.181",
      "unrealisedPnl": "0.61128",
      "leverage": "10",
      "takeProfit": "0.16404",
      "stopLoss": "0.17326"
    },
    {
      "symbol": "ADAUSDT",
      "side": "Sell",
      "size": "432",
      "avgPrice": "0.1619",
      "markPrice": "0.1616",
      "liqPrice": "0.1767",
      "unrealisedPnl": "0.1296",
      "leverage": "10",
      "takeProfit": "0.1595",
      "stopLoss": "0.1683"
    },
    {
      "symbol": "METISUSDT",
      "side": "Sell",
      "size": "27.7",
      "avgPrice": "2.517",
      "markPrice": "2.548",
      "liqPrice": "2.701",
      "unrealisedPnl": "-0.8587",
      "leverage": "10",
      "takeProfit": "2.494",
      "stopLoss": "2.628"
    },
    {
      "symbol": "DOGEUSDT",
      "side": "Sell",
      "size": "842",
      "avgPrice": "0.08311",
      "markPrice": "0.08294",
      "liqPrice": "0.09074",
      "unrealisedPnl": "0.14314",
      "leverage": "10",
      "takeProfit": "0.0822",
      "stopLoss": "0.08641"
    },
    {
      "symbol": "LINKUSDT",
      "side": "Sell",
      "size": "9.4",
      "avgPrice": "7.463",
      "markPrice": "7.417",
      "liqPrice": "8.128",
      "unrealisedPnl": "0.4324",
      "leverage": "10",
      "takeProfit": "7.368",
      "stopLoss": "7.752"
    },
    {
      "symbol": "SOLUSDT",
      "side": "Sell",
      "size": "1.1",
      "avgPrice": "65.07",
      "markPrice": "64.81",
      "liqPrice": "71.22",
      "unrealisedPnl": "0.286",
      "leverage": "10",
      "takeProfit": "64.25",
      "stopLoss": "67.63"
    },
    {
      "symbol": "XLMUSDT",
      "side": "Sell",
      "size": "366",
      "avgPrice": "0.191",
      "markPrice": "0.19139",
      "liqPrice": "0.20801",
      "unrealisedPnl": "-0.14274",
      "leverage": "10",
      "takeProfit": "0.18873",
      "stopLoss": "0.19861"
    },
    {
      "symbol": "XTZUSDT",
      "side": "Sell",
      "size": "278",
      "avgPrice": "0.25061457",
      "markPrice": "0.2519",
      "liqPrice": "0.2729",
      "unrealisedPnl": "-0.35735",
      "leverage": "10",
      "takeProfit": "0.2487",
      "stopLoss": "0.261"
    },
    {
      "symbol": "AVAXUSDT",
      "side": "Sell",
      "size": "10.1",
      "avgPrice": "6.954",
      "markPrice": "7.02",
      "liqPrice": "7.573",
      "unrealisedPnl": "-0.6666",
      "leverage": "10",
      "takeProfit": "6.877",
      "stopLoss": "7.234"
    },
    {
      "symbol": "IMXUSDT",
      "side": "Sell",
      "size": "535",
      "avgPrice": "0.13030084",
      "markPrice": "0.13221",
      "liqPrice": "0.14219",
      "unrealisedPnl": "-1.021399",
      "leverage": "10",
      "takeProfit": "0.12937",
      "stopLoss": "0.13603"
    },
    {
      "symbol": "SEIUSDT",
      "side": "Sell",
      "size": "1468",
      "avgPrice": "0.04754",
      "markPrice": "0.04795",
      "liqPrice": "0.05177",
      "unrealisedPnl": "-0.60188",
      "leverage": "10",
      "takeProfit": "0.04707",
      "stopLoss": "0.04956"
    },
    {
      "symbol": "IPUSDT",
      "side": "Sell",
      "size": "213",
      "avgPrice": "0.3279",
      "markPrice": "0.3296",
      "liqPrice": "0.3571",
      "unrealisedPnl": "-0.3621",
      "leverage": "10",
      "takeProfit": "0.3243",
      "stopLoss": "0.3413"
    },
    {
      "symbol": "HYPEUSDT",
      "side": "Sell",
      "size": "1",
      "avgPrice": "61.13241",
      "markPrice": "62.068",
      "liqPrice": "66.798",
      "unrealisedPnl": "-0.93559",
      "leverage": "10",
      "takeProfit": "60.382",
      "stopLoss": "63.642"
    },
    {
      "symbol": "FIDAUSDT",
      "side": "Sell",
      "size": "3794",
      "avgPrice": "0.0184974",
      "markPrice": "0.0185",
      "liqPrice": "0.01985",
      "unrealisedPnl": "-0.009859",
      "leverage": "10",
      "takeProfit": "0.018217",
      "stopLoss": "0.019188"
    },
    {
      "symbol": "BCHUSDT",
      "side": "Sell",
      "size": "0.32",
      "avgPrice": "216.7",
      "markPrice": "219.2",
      "liqPrice": "236",
      "unrealisedPnl": "-0.8",
      "leverage": "10",
      "takeProfit": "213.5",
      "stopLoss": "225.1"
    },
    {
      "symbol": "BNTUSDT",
      "side": "Sell",
      "size": "262",
      "avgPrice": "0.2661",
      "markPrice": "0.2652",
      "liqPrice": "0.2902",
      "unrealisedPnl": "0.2358",
      "leverage": "5",
      "takeProfit": "0.2632",
      "stopLoss": "0.2773"
    }
  ],
  "timestamp": "2026-06-05T10:25:18.890829-04:00"
}