{
  "positions": [
    {
      "symbol": "IMXUSDT",
      "side": "Buy",
      "size": "343",
      "avgPrice": "0.14259",
      "markPrice": "0.14156",
      "liqPrice": "0.12321",
      "unrealisedPnl": "-0.35329",
      "leverage": "7",
      "takeProfit": "0.14449",
      "stopLoss": "0.13454"
    },
    {
      "symbol": "IPUSDT",
      "side": "Buy",
      "size": "152",
      "avgPrice": "0.3218",
      "markPrice": "0.3179",
      "liqPrice": "0.2787",
      "unrealisedPnl": "-0.5928",
      "leverage": "7",
      "takeProfit": "0.3257",
      "stopLoss": "0.3036"
    },
    {
      "symbol": "FIDAUSDT",
      "side": "Buy",
      "size": "1816",
      "avgPrice": "0.02707668",
      "markPrice": "0.026966",
      "liqPrice": "0.023804",
      "unrealisedPnl": "-0.200995",
      "leverage": "7",
      "takeProfit": "0.027421",
      "stopLoss": "0.025429"
    },
    {
      "symbol": "SEIUSDT",
      "side": "Buy",
      "size": "972",
      "avgPrice": "0.0504045",
      "markPrice": "0.05028",
      "liqPrice": "0.04365",
      "unrealisedPnl": "-0.12101",
      "leverage": "7",
      "takeProfit": "0.05079",
      "stopLoss": "0.04749"
    },
    {
      "symbol": "OPUSDT",
      "side": "Buy",
      "size": "493",
      "avgPrice": "0.09948",
      "markPrice": "0.0992",
      "liqPrice": "0.08613",
      "unrealisedPnl": "-0.13804",
      "leverage": "7",
      "takeProfit": "0.10036",
      "stopLoss": "0.09372"
    },
    {
      "symbol": "LINKUSDT",
      "side": "Buy",
      "size": "6.1",
      "avgPrice": "7.993",
      "markPrice": "7.987",
      "liqPrice": "6.921",
      "unrealisedPnl": "-0.0366",
      "leverage": "7",
      "takeProfit": "8.052",
      "stopLoss": "7.542"
    },
    {
      "symbol": "SOLUSDT",
      "side": "Buy",
      "size": "0.7",
      "avgPrice": "67",
      "markPrice": "66.86",
      "liqPrice": "57.72",
      "unrealisedPnl": "-0.098",
      "leverage": "7",
      "takeProfit": "67.39",
      "stopLoss": "63.22"
    },
    {
      "symbol": "JASMYUSDT",
      "side": "Buy",
      "size": "17338",
      "avgPrice": "0.00484185",
      "markPrice": "0.00477",
      "liqPrice": "0.004193",
      "unrealisedPnl": "-1.24575",
      "leverage": "7",
      "takeProfit": "0.004875",
      "stopLoss": "0.004738"
    },
    {
      "symbol": "TONUSDT",
      "side": "Buy",
      "size": "28",
      "avgPrice": "1.7524",
      "markPrice": "1.7334",
      "liqPrice": "1.5173",
      "unrealisedPnl": "-0.532",
      "leverage": "7",
      "takeProfit": "1.7649",
      "stopLoss": "1.6508"
    },
    {
      "symbol": "GLMUSDT",
      "side": "Buy",
      "size": "428",
      "avgPrice": "0.11457192",
      "markPrice": "0.11396",
      "liqPrice": "0.10021",
      "unrealisedPnl": "-0.2619",
      "leverage": "7",
      "takeProfit": "0.11493",
      "stopLoss": "0.10773"
    },
    {
      "symbol": "TRXUSDT",
      "side": "Buy",
      "size": "149",
      "avgPrice": "0.32775",
      "markPrice": "0.32664",
      "liqPrice": "0.28306",
      "unrealisedPnl": "-0.16539",
      "leverage": "7",
      "takeProfit": "0.32836",
      "stopLoss": "0.30905"
    },
    {
      "symbol": "NEOUSDT",
      "side": "Buy",
      "size": "22.2",
      "avgPrice": "2.203",
      "markPrice": "2.201",
      "liqPrice": "1.908",
      "unrealisedPnl": "-0.0444",
      "leverage": "7",
      "takeProfit": "2.219",
      "stopLoss": "2.079"
    },
    {
      "symbol": "FILUSDT",
      "side": "Buy",
      "size": "125.7",
      "avgPrice": "0.78046094",
      "markPrice": "0.7813",
      "liqPrice": "0.6827",
      "unrealisedPnl": "0.10547",
      "leverage": "7",
      "takeProfit": "0.7879",
      "stopLoss": "0.7373"
    },
    {
      "symbol": "DYDXUSDT",
      "side": "Buy",
      "size": "339",
      "avgPrice": "0.14452",
      "markPrice": "0.1437",
      "liqPrice": "0.12513",
      "unrealisedPnl": "-0.27798",
      "leverage": "7",
      "takeProfit": "0.14692",
      "stopLoss": "0.13624"
    }
  ],
  "timestamp": "2026-06-08T09:20:20.062716-04:00"
}