{
  "config": {
    "capital": 1,
    "leverage": 10,
    "min_prob": 65,
    "tp_pct": 83,
    "start_date": "2026-06-02",
    "mode": "LIVE"
  },
  "trades_15m": [
    {
      "id": 1,
      "coin": "SOL",
      "tf": "15m",
      "direction": "SHORT",
      "entry": 77.39,
      "tp": 76.67916429,
      "liq": 85.090305,
      "size": 0.1292,
      "margin": 1,
      "probability": 67,
      "open_time": "2026-06-02T10:45:54",
      "close_time": "2026-06-02T11:20:31",
      "close_price": 76.67916429,
      "close_reason": "TP",
      "pnl": 0.09,
      "roi": 9.18,
      "status": "closed",
      "bybit_symbol": "SOLUSDT",
      "bybit_order_id": "cb261b81-b64b-4b3a-b767-3584c41f18d7",
      "bybit_qty": "0.1",
      "mode": "LIVE"
    },
    {
      "id": 2,
      "coin": "SUI",
      "tf": "15m",
      "direction": "SHORT",
      "entry": 0.8387,
      "tp": 0.82655236,
      "liq": 0.92215065,
      "size": 11.9232,
      "margin": 1,
      "probability": 66,
      "open_time": "2026-06-02T10:47:27",
      "close_time": "2026-06-02T11:20:31",
      "close_price": 0.82655236,
      "close_reason": "TP",
      "pnl": 0.14,
      "roi": 14.48,
      "status": "closed",
      "bybit_symbol": "SUIUSDT",
      "bybit_order_id": "70bfbba6-2002-4314-bda4-004c300d1b08",
      "bybit_qty": "11",
      "mode": "LIVE"
    }
  ],
  "trades_30m": [],
  "trades_1h": [],
  "trades_4h": [],
  "stats_15m": {
    "total": 2,
    "wins": 2,
    "losses": 0,
    "winrate": 100.0,
    "total_pnl": 0.23,
    "avg_pnl": 0.12,
    "avg_duration": "33m",
    "open": 0
  },
  "stats_30m": {
    "total": 0,
    "wins": 0,
    "losses": 0,
    "winrate": 0.0,
    "total_pnl": 0.0,
    "avg_pnl": 0.0,
    "avg_duration": "0m"
  },
  "stats_1h": {
    "total": 0,
    "wins": 0,
    "losses": 0,
    "winrate": 0.0,
    "total_pnl": 0.0,
    "avg_pnl": 0.0,
    "avg_duration": "0m"
  },
  "stats_4h": {
    "total": 0,
    "wins": 0,
    "losses": 0,
    "winrate": 0.0,
    "total_pnl": 0.0,
    "avg_pnl": 0.0,
    "avg_duration": "0m"
  }
}