{
  "positions": [
    {
      "symbol": "GLMUSDT",
      "side": "Buy",
      "size": "615",
      "avgPrice": "0.11388",
      "markPrice": "0.11353",
      "liqPrice": "0.10459",
      "unrealisedPnl": "-0.21525",
      "leverage": "10",
      "takeProfit": "0.11424",
      "stopLoss": "0.10918"
    },
    {
      "symbol": "TONUSDT",
      "side": "Buy",
      "size": "38.7",
      "avgPrice": "1.80744574",
      "markPrice": "1.7665",
      "liqPrice": "1.6432",
      "unrealisedPnl": "-1.5846",
      "leverage": "10",
      "takeProfit": "1.8281",
      "stopLoss": "1.7343"
    },
    {
      "symbol": "IMXUSDT",
      "side": "Buy",
      "size": "343",
      "avgPrice": "0.14259",
      "markPrice": "0.14023",
      "liqPrice": "0.12321",
      "unrealisedPnl": "-0.80948",
      "leverage": "7",
      "takeProfit": "0.14449",
      "stopLoss": "0.13454"
    },
    {
      "symbol": "IPUSDT",
      "side": "Buy",
      "size": "152",
      "avgPrice": "0.3218",
      "markPrice": "0.3113",
      "liqPrice": "0.2787",
      "unrealisedPnl": "-1.596",
      "leverage": "7",
      "takeProfit": "0.3257",
      "stopLoss": "0.3036"
    },
    {
      "symbol": "HBARUSDT",
      "side": "Buy",
      "size": "853",
      "avgPrice": "0.08205",
      "markPrice": "0.08148",
      "liqPrice": "0.07441",
      "unrealisedPnl": "-0.48621",
      "leverage": "10",
      "takeProfit": "0.08243",
      "stopLoss": "0.07876"
    },
    {
      "symbol": "DYDXUSDT",
      "side": "Buy",
      "size": "578",
      "avgPrice": "0.14503878",
      "markPrice": "0.14145",
      "liqPrice": "0.1343",
      "unrealisedPnl": "-2.074316",
      "leverage": "12",
      "takeProfit": "0.14637",
      "stopLoss": "0.14026"
    },
    {
      "symbol": "ADAUSDT",
      "side": "Buy",
      "size": "491",
      "avgPrice": "0.171",
      "markPrice": "0.1698",
      "liqPrice": "0.158",
      "unrealisedPnl": "-0.5892",
      "leverage": "12",
      "takeProfit": "0.1725",
      "stopLoss": "0.1653"
    },
    {
      "symbol": "ICPUSDT",
      "side": "Buy",
      "size": "35.1",
      "avgPrice": "2.392",
      "markPrice": "2.347",
      "liqPrice": "2.215",
      "unrealisedPnl": "-1.5795",
      "leverage": "12",
      "takeProfit": "2.407",
      "stopLoss": "2.31"
    },
    {
      "symbol": "HYPEUSDT",
      "side": "Buy",
      "size": "1",
      "avgPrice": "65.00977",
      "markPrice": "63.663",
      "liqPrice": "59.995",
      "unrealisedPnl": "-1.34677",
      "leverage": "12",
      "takeProfit": "65.932",
      "stopLoss": "62.997"
    },
    {
      "symbol": "TRXUSDT",
      "side": "Buy",
      "size": "149",
      "avgPrice": "0.32775",
      "markPrice": "0.32612",
      "liqPrice": "0.28306",
      "unrealisedPnl": "-0.24287",
      "leverage": "7",
      "takeProfit": "0.32836",
      "stopLoss": "0.30905"
    },
    {
      "symbol": "CFXUSDT",
      "side": "Buy",
      "size": "1804",
      "avgPrice": "0.04656",
      "markPrice": "0.04611",
      "liqPrice": "0.04356",
      "unrealisedPnl": "-0.8118",
      "leverage": "12",
      "takeProfit": "0.04685",
      "stopLoss": "0.04498"
    },
    {
      "symbol": "LINKUSDT",
      "side": "Buy",
      "size": "10.4",
      "avgPrice": "8.059",
      "markPrice": "8.022",
      "liqPrice": "7.463",
      "unrealisedPnl": "-0.3848",
      "leverage": "12",
      "takeProfit": "8.11",
      "stopLoss": "7.79"
    },
    {
      "symbol": "SEIUSDT",
      "side": "Buy",
      "size": "972",
      "avgPrice": "0.0504045",
      "markPrice": "0.04991",
      "liqPrice": "0.04365",
      "unrealisedPnl": "-0.48065",
      "leverage": "7",
      "takeProfit": "0.05079",
      "stopLoss": "0.04749"
    },
    {
      "symbol": "OPUSDT",
      "side": "Buy",
      "size": "493",
      "avgPrice": "0.09948",
      "markPrice": "0.09702",
      "liqPrice": "0.08613",
      "unrealisedPnl": "-1.21278",
      "leverage": "7",
      "takeProfit": "0.10036",
      "stopLoss": "0.09372"
    },
    {
      "symbol": "SOLUSDT",
      "side": "Buy",
      "size": "1.2",
      "avgPrice": "67.76",
      "markPrice": "67.149",
      "liqPrice": "62.43",
      "unrealisedPnl": "-0.7332",
      "leverage": "12",
      "takeProfit": "67.95",
      "stopLoss": "65.5"
    },
    {
      "symbol": "NEOUSDT",
      "side": "Buy",
      "size": "37.8",
      "avgPrice": "2.222",
      "markPrice": "2.183",
      "liqPrice": "2.058",
      "unrealisedPnl": "-1.4742",
      "leverage": "12",
      "takeProfit": "2.236",
      "stopLoss": "2.149"
    }
  ],
  "timestamp": "2026-06-08T16:35:16.641634-04:00"
}