{
  "positions": [
    {
      "symbol": "APTUSDT",
      "side": "Sell",
      "size": "112.3",
      "avgPrice": "0.6218",
      "markPrice": "0.619",
      "liqPrice": "0.6772",
      "unrealisedPnl": "0.31444",
      "leverage": "10",
      "takeProfit": "0.6154",
      "stopLoss": "0.6482"
    },
    {
      "symbol": "JUPUSDT",
      "side": "Sell",
      "size": "474",
      "avgPrice": "0.1475",
      "markPrice": "0.14694",
      "liqPrice": "0.16064",
      "unrealisedPnl": "0.26544",
      "leverage": "10",
      "takeProfit": "0.14596",
      "stopLoss": "0.1535"
    },
    {
      "symbol": "HBARUSDT",
      "side": "Sell",
      "size": "913",
      "avgPrice": "0.07655",
      "markPrice": "0.07677",
      "liqPrice": "0.08357",
      "unrealisedPnl": "-0.20086",
      "leverage": "10",
      "takeProfit": "0.07598",
      "stopLoss": "0.07967"
    },
    {
      "symbol": "TRXUSDT",
      "side": "Sell",
      "size": "220",
      "avgPrice": "0.31817145",
      "markPrice": "0.31826",
      "liqPrice": "0.34738",
      "unrealisedPnl": "-0.01948",
      "leverage": "10",
      "takeProfit": "0.31746",
      "stopLoss": "0.33081"
    },
    {
      "symbol": "SEIUSDT",
      "side": "Sell",
      "size": "1553",
      "avgPrice": "0.04504",
      "markPrice": "0.04475",
      "liqPrice": "0.04905",
      "unrealisedPnl": "0.45037",
      "leverage": "10",
      "takeProfit": "0.04458",
      "stopLoss": "0.04687"
    },
    {
      "symbol": "IPUSDT",
      "side": "Sell",
      "size": "231",
      "avgPrice": "0.302",
      "markPrice": "0.3011",
      "liqPrice": "0.3289",
      "unrealisedPnl": "0.2079",
      "leverage": "10",
      "takeProfit": "0.2991",
      "stopLoss": "0.3144"
    },
    {
      "symbol": "JASMYUSDT",
      "side": "Sell",
      "size": "16320",
      "avgPrice": "0.004274",
      "markPrice": "0.004273",
      "liqPrice": "0.004654",
      "unrealisedPnl": "0.016362",
      "leverage": "10",
      "takeProfit": "0.004245",
      "stopLoss": "0.00446"
    },
    {
      "symbol": "FILUSDT",
      "side": "Buy",
      "size": "100.9",
      "avgPrice": "0.69317076",
      "markPrice": "0.6778",
      "liqPrice": "0.6366",
      "unrealisedPnl": "-1.55091",
      "leverage": "10",
      "takeProfit": "0.7028",
      "stopLoss": "0.6662"
    }
  ],
  "timestamp": "2026-06-06T00:40:16.255935-04:00"
}